<?xml version="1.0" encoding="utf-8" ?>
<dwsync>
<file name="fckplugin.js" server="www.twe-shop.url.tw//www/shop/" local="129119698460000000" remote="130148618400000000" />
<file name="flvPlayer.gif" server="www.twe-shop.url.tw//www/shop/" local="129076750360000000" remote="130148618400000000" />
<file name="flvPlayer.html" server="www.twe-shop.url.tw//www/shop/" local="129076750360000000" remote="130148618400000000" />
<file name="flvPlayer.js" server="www.twe-shop.url.tw//www/shop/" local="129119698460000000" remote="130148618400000000" />
<file name="flvPlayer_recommendations_sample.xml" server="www.twe-shop.url.tw//www/shop/" local="129076750360000000" remote="130148618400000000" />
<file name="flvPlayer_rss_sample.xml" server="www.twe-shop.url.tw//www/shop/" local="129076750360000000" remote="130148618400000000" />
<file name="flvPlayer_xspf_sample.xml" server="www.twe-shop.url.tw//www/shop/" local="129076750360000000" remote="130148618400000000" />
<file name="JW_FLV_MEDIA_PLAYER_README.HTML" server="www.twe-shop.url.tw//www/shop/" local="129076750360000000" remote="130148618400000000" />
<file name="mediaplayer.html" server="www.twe-shop.url.tw//www/shop/" local="129119698460000000" remote="130148618400000000" />
<file name="mediaplayer.swf" server="www.twe-shop.url.tw//www/shop/" local="129076750360000000" remote="130148618400000000" />
<file name="readme.html" server="www.twe-shop.url.tw//www/shop/" local="129076750360000000" remote="130148618400000000" />
<file name="swfobject.js" server="www.twe-shop.url.tw//www/shop/" local="129076750360000000" remote="130148618400000000" />
<file name="flvPlayer.js" server="swid.taiwan-so.com//swid/" local="129119698460000000" remote="130148979000000000" />
<file name="swfobject.js" server="swid.taiwan-so.com//swid/" local="129076750360000000" remote="130148979000000000" />
<file name="fckplugin.js" server="swid.taiwan-so.com//swid/" local="129119698460000000" remote="130148979000000000" />
<file name="flvPlayer.gif" server="swid.taiwan-so.com//swid/" local="129076750360000000" remote="130148979000000000" />
<file name="flvPlayer.html" server="swid.taiwan-so.com//swid/" local="129076750360000000" remote="130148979000000000" />
<file name="flvPlayer_recommendations_sample.xml" server="swid.taiwan-so.com//swid/" local="129076750360000000" remote="130148979000000000" />
<file name="flvPlayer_rss_sample.xml" server="swid.taiwan-so.com//swid/" local="129076750360000000" remote="130148979000000000" />
<file name="flvPlayer_xspf_sample.xml" server="swid.taiwan-so.com//swid/" local="129076750360000000" remote="130148979000000000" />
<file name="JW_FLV_MEDIA_PLAYER_README.HTML" server="swid.taiwan-so.com//swid/" local="129076750360000000" remote="130148979000000000" />
<file name="mediaplayer.html" server="swid.taiwan-so.com//swid/" local="129119698460000000" remote="130148979000000000" />
<file name="mediaplayer.swf" server="swid.taiwan-so.com//swid/" local="129076750360000000" remote="130148979000000000" />
<file name="readme.html" server="swid.taiwan-so.com//swid/" local="129076750360000000" remote="130148979000000000" />
</dwsync>